CHANGES.rst
CONTRIBUTORS.rst
MANIFEST.in
README.rst
base.cfg
buildout.cfg
setup.cfg
setup.py
test_plone51.cfg
test_plone52.cfg
travis.cfg
docs/LICENSE.GPL
docs/LICENSE.rst
docs/index.rst
src/collective/__init__.py
src/collective.isotope.egg-info/PKG-INFO
src/collective.isotope.egg-info/SOURCES.txt
src/collective.isotope.egg-info/dependency_links.txt
src/collective.isotope.egg-info/entry_points.txt
src/collective.isotope.egg-info/namespace_packages.txt
src/collective.isotope.egg-info/not-zip-safe
src/collective.isotope.egg-info/requires.txt
src/collective.isotope.egg-info/top_level.txt
src/collective/isotope/__init__.py
src/collective/isotope/configure.zcml
src/collective/isotope/interfaces.py
src/collective/isotope/setuphandlers.py
src/collective/isotope/testing.py
src/collective/isotope/utilities.py
src/collective/isotope/vocabularies.py
src/collective/isotope/browser/__init__.py
src/collective/isotope/browser/configure.zcml
src/collective/isotope/browser/controlpanel.py
src/collective/isotope/browser/views.py
src/collective/isotope/browser/static/.gitkeep
src/collective/isotope/browser/static/isotope-display.less
src/collective/isotope/browser/static/isotope.pkgd.js
src/collective/isotope/browser/static/isotope.pkgd.min.js
src/collective/isotope/browser/templates/isotope.pt
src/collective/isotope/locales/collective.isotope.pot
src/collective/isotope/locales/update.sh
src/collective/isotope/profiles/default/actions.xml
src/collective/isotope/profiles/default/browserlayer.xml
src/collective/isotope/profiles/default/collectiveisotope_default.txt
src/collective/isotope/profiles/default/controlpanel.xml
src/collective/isotope/profiles/default/metadata.xml
src/collective/isotope/profiles/default/registry.xml
src/collective/isotope/profiles/default/types/Collection.xml
src/collective/isotope/profiles/default/types/Folder.xml
src/collective/isotope/profiles/uninstall/browserlayer.xml
src/collective/isotope/profiles/uninstall/collectiveisotope_uninstall.txt
src/collective/isotope/tests/__init__.py
src/collective/isotope/tests/test_setup.py