Metadata-Version: 2.1
Name: collective.isotope
Version: 0.2
Summary: Plone view for folders and collections using the Isotope jquery plugin
Home-page: http://pypi.python.org/pypi/collective.isotope
Author: cewing
Author-email: cris@crisewing.com
License: GPL version 2
Keywords: Python Plone
Platform: UNKNOWN
Classifier: Environment :: Web Environment
Classifier: Framework :: Plone
Classifier: Framework :: Plone :: 5.0
Classifier: Framework :: Plone :: 5.2
Classifier: Framework :: Plone :: 5.2
Classifier: Programming Language :: Python
Classifier: Programming Language :: Python :: 2.7
Classifier: Operating System :: OS Independent
Classifier: License :: OSI Approved :: GNU General Public License v2 (GPLv2)
Provides-Extra: test
